massmigration/__init__.py
massmigration/admin.py
massmigration/api.py
massmigration/constants.py
massmigration/enforcement.py
massmigration/exceptions.py
massmigration/fields.py
massmigration/loader.py
massmigration/migrations.py
massmigration/models.py
massmigration/record_cache.py
massmigration/urls.py
massmigration/views.py
massmigration/backends/__init__.py
massmigration/backends/base.py
massmigration/backends/djangae.py
massmigration/management/__init__.py
massmigration/management/commands/__init__.py
massmigration/management/commands/makemassmigration.py
massmigration/templates/admin/massmigration/migrationrecord/change_list.html
massmigration/templates/massmigration/base.html
massmigration/templates/massmigration/delete_migration.html
massmigration/templates/massmigration/manage_migrations.html
massmigration/templates/massmigration/migration_detail.html
massmigration/templates/massmigration/run_migration.html
massmigration/templates/migration_templates/custom.py
massmigration/templates/migration_templates/mapper.py
massmigration/templates/migration_templates/simple.py
massmigration/tests/__init__.py
massmigration/tests/test_commands.py
massmigration/tests/test_loader.py
massmigration/utils/__init__.py
massmigration/utils/apps.py
massmigration/utils/functional.py
massmigration/utils/permissions.py
massmigration/utils/test.py
massmigration/utils/transaction.py
testing/__init__.py
testing/test_settings.py
django_mass_migration-0.3.9.dist-info/LICENSE
django_mass_migration-0.3.9.dist-info/METADATA
django_mass_migration-0.3.9.dist-info/WHEEL
django_mass_migration-0.3.9.dist-info/top_level.txt
django_mass_migration-0.3.9.dist-info/RECORD
