Metadata-Version: 2.1
Name: django-mass-migration
Version: 0.3.9
Summary: Django app for long-running data migrations
Home-page: https://github.com/adamalton/django-mass-migration
Author: Adam Alton
Keywords: django,djangae,django-gcloud-connectors,Google App Engine
Classifier: Development Status :: 4 - Beta
Classifier: Framework :: Django
Classifier: Framework :: Django :: 3.2
Classifier: Framework :: Django :: 4.1
Classifier: Framework :: Django :: 4.2
Classifier: Framework :: Django :: 5.0
Classifier: Framework :: Django :: 5.1
Classifier: Framework :: Django :: 5.2
Classifier: Intended Audience :: Developers
Classifier: License :: OSI Approved :: MIT License
Classifier: Operating System :: OS Independent
Classifier: Programming Language :: Python
License-File: LICENSE
Requires-Dist: django<6.0,>=3.2
Requires-Dist: djangae>=1.1.0
Requires-Dist: django-gcloud-connectors>=0.3.6
